dataramp/__init__.py
dataramp/cli.py
dataramp/core.py
dataramp/eval.py
dataramp/exceptions.py
dataramp/feature_engineering.py
dataramp/load_data.py
dataramp/model_train.py
dataramp/outlier.py
dataramp/utils.py
dataramp/visualizer.py
docs/README.md
docs/build/_sources/index.rst.txt
docs/source/conf.py
examples/examp_project/README.md
examples/examp_project/requirements.txt
examples/hello-world/README.md
dataramp-0.3.5.dist-info/METADATA
dataramp-0.3.5.dist-info/WHEEL
dataramp-0.3.5.dist-info/top_level.txt
dataramp-0.3.5.dist-info/RECORD
